bite/__init__.py
bite/io.py
bite/parse_functions.py
bite/parsers.py
bite/tests/__init__.py
bite/tests/mock_reader.py
bite/tests/test_io.py
bite/tests/test_parse_functions.py
bite/tests/test_parsers.py
bite/tests/test_transformers.py
bite/transformers.py
bite_parser-0.2.5.dist-info/LICENSE
bite_parser-0.2.5.dist-info/METADATA
bite_parser-0.2.5.dist-info/WHEEL
bite_parser-0.2.5.dist-info/RECORD
