Metadata-Version: 2.1
Name: bite-parser
Version: 0.2.5
Summary: Asynchronous parser taking incremental bites out of your byte input stream.
Home-page: https://github.com/jgosmann/bite-parser/
License: MIT
Keywords: asyncio,parser,PEG,incremental,parser expression grammar
Author: Jan Gosmann
Author-email: jan@hyper-world.de
Requires-Python: >=3.9,<4.0
Classifier: Development Status :: 3 - Alpha
Classifier: Framework :: AsyncIO
Classifier: Intended Audience :: Developers
Classifier: License :: OSI Approved :: MIT License
Classifier: Programming Language :: Python :: 3
Classifier: Programming Language :: Python :: 3.9
Classifier: Programming Language :: Python :: 3.10
Classifier: Programming Language :: Python :: 3.11
Classifier: Programming Language :: Python :: 3.12
Classifier: Programming Language :: Python :: 3.13
Classifier: Programming Language :: Python :: 3 :: Only
Classifier: Topic :: Software Development :: Compilers
Classifier: Topic :: Software Development :: Libraries :: Python Modules
Project-URL: Repository, https://github.com/jgosmann/bite-parser/
